hexlet/graphs.py
hexlet_graphs-0.1.3.dist-info/LICENSE
hexlet_graphs-0.1.3.dist-info/WHEEL
hexlet_graphs-0.1.3.dist-info/METADATA
hexlet_graphs-0.1.3.dist-info/RECORD
